{
    "报告信息": {
        "序号": null,
        "股票代码": "600535",
        "股票简称": "天士力",
        "报告年份": "2024",
        "报告期": "FY",
        "总股本_股": 1494950005,
        "流通股本_股": null,
        "报告日期": "2023-12-31",
        "审计意见": "标准无保留意见",
        "会计师事务所": "天健会计师事务所（特殊普通合伙）"
    },
    "核心业绩指标": {
        "每股收益_元": 0.72,
        "稀释每股收益_元": 0.72,
        "营业总收入_万元": 867401.42,
        "营业总收入_亿元": 86.74,
        "营收同比增长_百分比": 0.42,
        "营收环比增长_百分比": null,
        "净利润_万元": 101664.0,
        "净利润_亿元": 10.17,
        "净利润同比增长_百分比": null,
        "净利润环比增长_百分比": null,
        "归母净利润_万元": 107107.23,
        "少数股东损益_万元": -5429.92,
        "每股净资产_元": null,
        "净资产收益率_百分比": 8.75,
        "扣非净资产收益率_百分比": null,
        "每股经营现金流_元": 1.723,
        "扣非净利润_万元": 118114.95,
        "扣非净利润同比增长_百分比": 60.11,
        "销售毛利率_百分比": 66.85,
        "销售净利率_百分比": 11.72,
        "加权平均净资产收益率_百分比": 8.75,
        "扣非加权净资产收益率_百分比": 9.65,
        "总资产收益率_百分比": 6.08,
        "主营业务收入_万元": 863630.51,
        "主营业务成本_万元": 286299.45,
        "主营业务利润_万元": null
    },
    "资产负债表": {
        "货币资金_万元": 445060.07,
        "应收账款_万元": 68800.32,
        "应收票据_万元": null,
        "应收款项融资_万元": 144276.7,
        "预付款项_万元": 6557.24,
        "其他应收款_万元": 1149.01,
        "存货_万元": 174768.54,
        "合同资产_万元": null,
        "一年内到期的非流动资产_万元": null,
        "其他流动资产_万元": 2585.39,
        "流动资产合计_万元": 873268.09,
        "交易性金融资产_万元": 30070.82,
        "债权投资_万元": null,
        "其他债权投资_万元": null,
        "长期应收款_万元": null,
        "长期股权投资_万元": 141541.21,
        "其他权益工具投资_万元": null,
        "投资性房地产_万元": null,
        "固定资产_万元": 338871.87,
        "在建工程_万元": 15387.23,
        "生产性生物资产_万元": null,
        "油气资产_万元": null,
        "使用权资产_万元": 22660.0,
        "无形资产_万元": 57363.85,
        "开发支出_万元": 145289.7,
        "商誉_万元": 1588.04,
        "长期待摊费用_万元": 2322.27,
        "递延所得税资产_万元": 5000.33,
        "其他非流动资产_万元": 4314.23,
        "非流动资产合计_万元": 798160.42,
        "总资产_万元": 1671428.51,
        "总资产同比增长_百分比": 1.44,
        "短期借款_万元": 72305.11,
        "交易性金融负债_万元": null,
        "应付票据_万元": 12890.57,
        "应付账款_万元": 44382.01,
        "预收款项_万元": 6636.3,
        "合同负债_万元": 8901.53,
        "应付职工薪酬_万元": 11430.23,
        "应交税费_万元": 8561.21,
        "其他应付款_万元": 18390.62,
        "一年内到期的非流动负债_万元": 52127.87,
        "其他流动负债_万元": 1330.17,
        "流动负债合计_万元": 236955.63,
        "长期借款_万元": 141406.25,
        "应付债券_万元": null,
        "租赁负债_万元": 8152.22,
        "长期应付款_万元": null,
        "预计负债_万元": null,
        "递延收益_万元": 15902.46,
        "递延所得税负债_万元": 11.05,
        "其他非流动负债_万元": null,
        "非流动负债合计_万元": 165471.98,
        "总负债_万元": 402427.6,
        "总负债同比增长_百分比": 5.92,
        "资产负债率_百分比": 24.08,
        "实收资本_万元": 149970.01,
        "资本公积_万元": 95807.68,
        "盈余公积_万元": 163687.45,
        "未分配利润_万元": 829175.1,
        "其他综合收益_万元": 8799.89,
        "专项储备_万元": null,
        "归属于母公司所有者权益合计_万元": 1236842.01,
        "少数股东权益_万元": 32158.9,
        "股东权益合计_万元": 1269000.91
    },
    "利润表": {
        "营业总收入_万元": 867401.42,
        "营业收入_万元": 867401.42,
        "营业总收入同比增长_百分比": 0.42,
        "营业成本_万元": 288010.28,
        "税金及附加_万元": 12869.53,
        "销售费用_万元": 298352.57,
        "管理费用_万元": 34236.99,
        "研发费用_万元": 91726.91,
        "财务费用_万元": -1905.53,
        "其中利息费用_万元": 8252.44,
        "其中利息收入_万元": 10754.52,
        "其他收益_万元": 8275.39,
        "投资收益_万元": -11092.49,
        "其中对联营企业投资收益_万元": -13003.51,
        "公允价值变动收益_万元": -17188.44,
        "信用减值损失_万元": -819.3,
        "资产减值损失_万元": -512.48,
        "资产处置收益_万元": 14.63,
        "营业总支出_万元": null,
        "营业利润_万元": 122787.98,
        "营业外收入_万元": 305.9,
        "营业外支出_万元": 984.23,
        "利润总额_万元": 122109.66,
        "所得税费用_万元": 20445.65,
        "净利润_万元": 101664.0,
        "归母净利润_万元": 107107.23,
        "少数股东损益_万元": -5429.92,
        "持续经营净利润_万元": null,
        "终止经营净利润_万元": null,
        "其他综合收益_万元": null,
        "综合收益总额_万元": 89319.44,
        "归母综合收益总额_万元": 94749.36
    },
    "现金流量表": {
        "销售商品收到现金_万元": 1037260.33,
        "收到的税费返还_万元": 1759.45,
        "收到其他经营活动现金_万元": 21224.09,
        "经营活动现金流入_万元": 1060243.87,
        "购买商品支付现金_万元": 224198.08,
        "支付职工现金_万元": 196478.94,
        "支付税费_万元": 111649.56,
        "支付其他经营活动现金_万元": 270353.82,
        "经营活动现金流出_万元": 802680.41,
        "经营现金流净额_万元": 257563.46,
        "经营现金流净额同比增长_百分比": 12.98,
        "收回投资现金_万元": 164875.44,
        "取得投资收益现金_万元": 3116.82,
        "处置资产收回现金_万元": 119.15,
        "收到其他投资活动现金_万元": 7777.22,
        "投资活动现金流入_万元": 175888.63,
        "投资支付现金_万元": 178289.21,
        "购建资产支付现金_万元": 66881.89,
        "支付其他投资活动现金_万元": 141573.36,
        "投资活动现金流出_万元": 386744.46,
        "投资现金流净额_万元": -210855.83,
        "吸收投资现金_万元": 5.0,
        "取得借款现金_万元": 181724.44,
        "收到其他筹资活动现金_万元": 32306.7,
        "筹资活动现金流入_万元": 181729.44,
        "偿还债务现金_万元": 104000.0,
        "分配股利现金_万元": 56491.45,
        "支付其他筹资活动现金_万元": 151066.86,
        "筹资活动现金流出_万元": 311558.31,
        "融资现金流净额_万元": -129828.87,
        "汇率变动影响_万元": null,
        "现金及等价物净增加额_万元": -73053.81,
        "净现金流_元": null,
        "净现金流同比增长_百分比": null,
        "期初现金及等价物_万元": 292787.07,
        "期末现金及等价物_万元": 219733.26,
        "经营现金流占比_百分比": null,
        "投资现金流占比_百分比": null,
        "融资现金流占比_百分比": null
    }
}