{
    "报告信息": {
        "序号": null,
        "股票代码": "600976",
        "股票简称": "健民集团",
        "报告年份": "2025",
        "报告期": "年度报告",
        "总股本_股": 153398600,
        "流通股本_股": null,
        "报告日期": null,
        "审计意见": "标准无保留意见",
        "会计师事务所": "中审众环会计师事务所（特殊普通合伙）",
        "期": "FY"
    },
    "核心业绩指标": {
        "每股收益_元": 2.38,
        "稀释每股收益_元": 2.38,
        "营业总收入_万元": 350498.61,
        "营业总收入_亿元": 35.05,
        "营收同比增长_百分比": -16.81,
        "营收环比增长_百分比": null,
        "净利润_万元": 36217.87,
        "净利润_亿元": 3.62,
        "净利润同比增长_百分比": -30.54,
        "净利润环比增长_百分比": null,
        "归母净利润_万元": 36217.87,
        "少数股东损益_万元": -102.9,
        "每股净资产_元": 15.92,
        "净资产收益率_百分比": 15.68,
        "扣非净资产收益率_百分比": 13.13,
        "每股经营现金流_元": 1.53,
        "扣非净利润_万元": 30339.43,
        "扣非净利润同比增长_百分比": -30.8,
        "销售毛利率_百分比": 47.77,
        "销售净利率_百分比": 10.33,
        "加权平均净资产收益率_百分比": 15.68,
        "扣非加权净资产收益率_百分比": 13.13,
        "总资产收益率_百分比": 8.46,
        "主营业务收入_万元": 348385.72,
        "主营业务成本_万元": 182202.18,
        "主营业务利润_万元": 166183.54
    },
    "资产负债表": {
        "货币资金_万元": 16317.39,
        "应收账款_万元": 80766.73,
        "应收票据_万元": 1993.89,
        "应收款项融资_万元": 12882.0,
        "坏账准备_其他应收款_万元": 3870.46,
        "存货_万元": 36282.58,
        "存货跌价准备_万元": 851.42,
        "存货账面价值_万元": 35431.16,
        "其他流动资产_万元": 5107.1,
        "长期股权投资_万元": 73902.19,
        "其他非流动金融资产_万元": 34210.01,
        "投资性房地产_万元": 822.87,
        "固定资产_万元": 36102.12,
        "在建工程_万元": 20667.98,
        "使用权资产_万元": 2789.14,
        "无形资产_万元": 2819.05,
        "商誉_万元": 21.4,
        "长期待摊费用_万元": 10799.5,
        "递延所得税资产_万元": 12949.03,
        "其他非流动资产_万元": 1151.0,
        "短期借款_万元": 14089.51,
        "应付票据_万元": 21483.9,
        "应付账款_万元": 52737.81,
        "合同负债_万元": 6143.14,
        "应付职工薪酬_万元": 4490.55,
        "应交税费_万元": 6160.55,
        "其他应付款_万元": 15138.7,
        "一年内到期的非流动负债_万元": 638.68,
        "其他流动负债_万元": 53618.84,
        "长期借款_万元": 400.0,
        "租赁负债_万元": 2443.05,
        "递延所得税负债_万元": 720.45,
        "递延收益_万元": 4655.24
    }
}