{
    "报告信息": {
        "序号": null,
        "股票代码": "603896",
        "股票简称": "寿仙谷",
        "报告年份": "2024",
        "报告期": "年度报告",
        "总股本_股": 201828618,
        "流通股本_股": 201828618,
        "报告日期": "2024-04-26",
        "审计意见": "标准无保留意见",
        "会计师事务所": "立信会计师事务所（特殊普通合伙）",
        "期": "FY"
    },
    "核心业绩指标": {
        "每股收益_元": 1.3,
        "稀释每股收益_元": 1.3,
        "营业总收入_万元": 78434.73,
        "营业总收入_亿元": 7.84,
        "营收同比增长_百分比": -5.39,
        "营收环比增长_百分比": null,
        "净利润_万元": 25448.01,
        "净利润_亿元": 2.54,
        "净利润同比增长_百分比": -8.39,
        "净利润环比增长_百分比": null,
        "归母净利润_万元": 25448.01,
        "少数股东损益_万元": null,
        "每股净资产_元": null,
        "净资产收益率_百分比": 12.44,
        "扣非净资产收益率_百分比": null,
        "每股经营现金流_元": null,
        "扣非净利润_万元": 22672.57,
        "扣非净利润同比增长_百分比": -10.45,
        "销售毛利率_百分比": null,
        "销售净利率_百分比": null,
        "加权平均净资产收益率_百分比": 12.44,
        "扣非加权净资产收益率_百分比": 11.08,
        "总资产收益率_百分比": null,
        "主营业务收入_万元": 77033.88,
        "主营业务成本_万元": 11995.77,
        "主营业务利润_万元": null
    },
    "资产负债表": {
        "货币资金_万元": 150396.25,
        "应收账款_万元": 9108.76,
        "应收票据_万元": 2084.45,
        "应收款项融资_万元": 113.2,
        "预付款项_万元": 2065.67,
        "其他应收款_万元": 325.32,
        "存货_万元": 15783.33,
        "合同资产_万元": null,
        "一年内到期的非流动资产_万元": null,
        "其他流动资产_万元": 807.62,
        "流动资产合计_万元": 180684.59,
        "交易性金融资产_万元": 0,
        "债权投资_万元": null,
        "其他债权投资_万元": null,
        "长期应收款_万元": null,
        "长期股权投资_万元": 573.82,
        "其他权益工具投资_万元": 5997.58,
        "投资性房地产_万元": 22376.26,
        "固定资产_万元": 33500.71,
        "在建工程_万元": 28020.85,
        "生产性生物资产_万元": 3138.35,
        "油气资产_万元": null,
        "使用权资产_万元": 3572.1,
        "无形资产_万元": 31097.73,
        "开发支出_万元": null,
        "商誉_万元": null,
        "长期待摊费用_万元": 7978.36,
        "递延所得税资产_万元": 46.17,
        "其他非流动资产_万元": 495.09,
        "非流动资产合计_万元": 136750.84,
        "总资产_万元": 317435.44,
        "总资产同比增长_百分比": 11.14,
        "短期借款_万元": 37216.07,
        "交易性金融负债_万元": null,
        "应付票据_万元": null,
        "应付账款_万元": 14581.82,
        "预收款项_万元": 112.88,
        "合同负债_万元": 897.59,
        "应付职工薪酬_万元": 2908.99,
        "应交税费_万元": 953.05,
        "其他应付款_万元": 536.32,
        "一年内到期的非流动负债_万元": 1207.94,
        "其他流动负债_万元": 100.01,
        "流动负债合计_万元": 58514.69,
        "长期借款_万元": null,
        "应付债券_万元": 34018.66,
        "租赁负债_万元": 2397.1,
        "长期应付款_万元": null,
        "预计负债_万元": null,
        "递延收益_万元": 4998.38,
        "递延所得税负债_万元": 377.74,
        "其他非流动负债_万元": null,
        "非流动负债合计_万元": 41791.88,
        "总负债_万元": 100306.57,
        "总负债同比增长_百分比": null,
        "资产负债率_百分比": 31.6,
        "实收资本_万元": 20182.86,
        "资本公积_万元": 96603.22,
        "盈余公积_万元": 10093.15,
        "未分配利润_万元": 97477.35,
        "其他综合收益_万元": 2305.69,
        "专项储备_万元": null,
        "归属于母公司所有者权益合计_万元": 217128.87,
        "少数股东权益_万元": null,
        "股东权益合计_万元": null
    },
    "利润表": {
        "营业总收入_万元": 78434.73,
        "营业收入_万元": 78434.73,
        "营业总收入同比增长_百分比": -5.39,
        "营业成本_万元": 13552.81,
        "税金及附加_万元": 890.65,
        "销售费用_万元": 31679.38,
        "管理费用_万元": 8699.18,
        "研发费用_万元": 4968.28,
        "财务费用_万元": -2303.87,
        "其中利息费用_万元": 2470.33,
        "其中利息收入_万元": 4808.67,
        "其他收益_万元": 3998.63,
        "投资收益_万元": 368.19,
        "其中对联营企业投资收益_万元": 37.57,
        "公允价值变动收益_万元": 27.14,
        "信用减值损失_万元": 112.72,
        "资产减值损失_万元": null,
        "资产处置收益_万元": 17.25,
        "营业总支出_万元": null,
        "营业利润_万元": 25472.24,
        "营业外收入_万元": 259.98,
        "营业外支出_万元": 241.13,
        "利润总额_万元": 25491.09,
        "所得税费用_万元": 43.09,
        "净利润_万元": 25448.01,
        "归母净利润_万元": 25448.01,
        "少数股东损益_万元": null,
        "持续经营净利润_万元": 25448.01,
        "终止经营净利润_万元": null,
        "其他综合收益_万元": 299.18,
        "综合收益总额_万元": 25747.19,
        "归母综合收益总额_万元": 25747.19
    },
    "现金流量表": {
        "销售商品收到现金_万元": 81425.8,
        "收到的税费返还_万元": null,
        "收到其他经营活动现金_万元": 11101.45,
        "经营活动现金流入_万元": 92527.25,
        "购买商品支付现金_万元": 9770.06,
        "支付职工现金_万元": 13261.52,
        "支付税费_万元": 4641.32,
        "支付其他经营活动现金_万元": 33348.61,
        "经营活动现金流出_万元": 61021.51,
        "经营现金流净额_万元": 31505.74,
        "经营现金流净额同比增长_百分比": -7.68,
        "收回投资现金_万元": 56311.23,
        "取得投资收益现金_万元": 253.64,
        "处置资产收回现金_万元": 11.38,
        "收到其他投资活动现金_万元": null,
        "投资活动现金流入_万元": 56576.25,
        "投资支付现金_万元": 18260.05,
        "购建资产支付现金_万元": 41454.04,
        "支付其他投资活动现金_万元": null,
        "投资活动现金流出_万元": 129878.3,
        "投资现金流净额_万元": -129878.3,
        "吸收投资现金_万元": null,
        "取得借款现金_万元": 73743.78,
        "收到其他筹资活动现金_万元": null,
        "筹资活动现金流入_万元": 99243.78,
        "偿还债务现金_万元": 60165.51,
        "分配股利现金_万元": 9277.96,
        "支付其他筹资活动现金_万元": null,
        "筹资活动现金流出_万元": 70235.65,
        "融资现金流净额_万元": 29008.13,
        "汇率变动影响_万元": null,
        "现金及等价物净增加额_万元": -32610.29,
        "净现金流_元": null,
        "净现金流同比增长_百分比": null,
        "期初现金及等价物_万元": 126971.24,
        "期末现金及等价物_万元": 94360.95,
        "经营现金流占比_百分比": null,
        "投资现金流占比_百分比": null,
        "融资现金流占比_百分比": null
    }
}