{
    "报告信息": {
        "序号": null,
        "股票代码": "300878",
        "股票简称": "维康药业",
        "报告年份": "2023",
        "报告期": "Q3",
        "总股本_股": 144790322,
        "流通股本_股": null,
        "报告日期": "2023-10-27",
        "审计意见": null,
        "会计师事务所": null
    },
    "核心业绩指标": {
        "每股收益_元": 0.479,
        "稀释每股收益_元": 0.479,
        "营业总收入_万元": 43200.17,
        "营业总收入_亿元": 4.32,
        "营收同比增长_百分比": -8.93,
        "营收环比增长_百分比": null,
        "净利润_万元": 7087.33,
        "净利润_亿元": 0.71,
        "净利润同比增长_百分比": -25.12,
        "净利润环比增长_百分比": null,
        "归母净利润_万元": 6935.06,
        "少数股东损益_万元": 152.27,
        "每股净资产_元": null,
        "净资产收益率_百分比": null,
        "扣非净资产收益率_百分比": null,
        "每股经营现金流_元": null,
        "扣非净利润_万元": 6410.97,
        "扣非净利润同比增长_百分比": -19.76,
        "销售毛利率_百分比": null,
        "销售净利率_百分比": null,
        "加权平均净资产收益率_百分比": 4.84,
        "扣非加权净资产收益率_百分比": null,
        "总资产收益率_百分比": null,
        "主营业务收入_万元": 43200.17,
        "主营业务成本_万元": 18081.67,
        "主营业务利润_万元": null
    },
    "资产负债表": {
        "货币资金_万元": 19580.6,
        "应收账款_万元": 32582.0,
        "应收票据_万元": null,
        "应收款项融资_万元": 1529.59,
        "预付款项_万元": 2583.71,
        "其他应收款_万元": 636.57,
        "存货_万元": 15887.17,
        "合同资产_万元": null,
        "一年内到期的非流动资产_万元": null,
        "其他流动资产_万元": 1355.93,
        "流动资产合计_万元": 98255.57,
        "交易性金融资产_万元": 24100.0,
        "债权投资_万元": null,
        "其他债权投资_万元": null,
        "长期应收款_万元": null,
        "长期股权投资_万元": null,
        "其他权益工具投资_万元": null,
        "投资性房地产_万元": 534.46,
        "固定资产_万元": 52738.24,
        "在建工程_万元": 43924.95,
        "生产性生物资产_万元": null,
        "油气资产_万元": null,
        "使用权资产_万元": 2294.51,
        "无形资产_万元": 3616.38,
        "开发支出_万元": null,
        "商誉_万元": 2709.63,
        "长期待摊费用_万元": 559.87,
        "递延所得税资产_万元": 1249.51,
        "其他非流动资产_万元": 81.3,
        "非流动资产合计_万元": 110208.84,
        "总资产_万元": 208464.41,
        "总资产同比增长_百分比": 8.93,
        "短期借款_万元": 28916.43,
        "交易性金融负债_万元": null,
        "应付票据_万元": 2113.69,
        "应付账款_万元": 7046.31,
        "预收款项_万元": 10.97,
        "合同负债_万元": 1541.12,
        "应付职工薪酬_万元": 826.95,
        "应交税费_万元": 203.88,
        "其他应付款_万元": 696.37,
        "一年内到期的非流动负债_万元": 1137.44,
        "其他流动负债_万元": 200.32,
        "流动负债合计_万元": 42682.52,
        "长期借款_万元": 12458.95,
        "应付债券_万元": null,
        "租赁负债_万元": 613.32,
        "长期应付款_万元": null,
        "预计负债_万元": null,
        "递延收益_万元": 3606.16,
        "递延所得税负债_万元": 622.35,
        "其他非流动负债_万元": null,
        "非流动负债合计_万元": 17300.78,
        "总负债_万元": 59983.3,
        "总负债同比增长_百分比": null,
        "资产负债率_百分比": null,
        "实收资本_万元": 14479.03,
        "资本公积_万元": 68076.5,
        "盈余公积_万元": 6099.05,
        "未分配利润_万元": 58112.3,
        "其他综合收益_万元": null,
        "专项储备_万元": null,
        "归属于母公司所有者权益合计_万元": 146766.89,
        "少数股东权益_万元": 1714.22,
        "股东权益合计_万元": 148481.11
    },
    "利润表": {
        "营业总收入_万元": 43200.17,
        "营业收入_万元": 43200.17,
        "营业总收入同比增长_百分比": -8.93,
        "营业成本_万元": 18081.67,
        "税金及附加_万元": 129.32,
        "销售费用_万元": 12356.83,
        "管理费用_万元": 2865.33,
        "研发费用_万元": 1986.62,
        "财务费用_万元": 522.47,
        "其中利息费用_万元": 611.56,
        "其中利息收入_万元": 140.01,
        "其他收益_万元": 526.03,
        "投资收益_万元": 720.35,
        "其中对联营企业投资收益_万元": null,
        "公允价值变动收益_万元": null,
        "信用减值损失_万元": 926.7,
        "资产减值损失_万元": -12.59,
        "资产处置收益_万元": 1.24,
        "营业总支出_万元": null,
        "营业利润_万元": 9419.65,
        "营业外收入_万元": 5.36,
        "营业外支出_万元": 516.16,
        "利润总额_万元": 8908.85,
        "所得税费用_万元": 1821.51,
        "净利润_万元": 7087.33,
        "归母净利润_万元": 6935.06,
        "少数股东损益_万元": 152.27,
        "持续经营净利润_万元": 7087.33,
        "终止经营净利润_万元": null,
        "其他综合收益_万元": null,
        "综合收益总额_万元": 7087.33,
        "归母综合收益总额_万元": 6935.06
    },
    "现金流量表": {
        "销售商品收到现金_万元": 38634.35,
        "收到的税费返还_万元": 15.09,
        "收到其他经营活动现金_万元": 1309.56,
        "经营活动现金流入_万元": 39959.0,
        "购买商品支付现金_万元": 14151.11,
        "支付职工现金_万元": 8330.96,
        "支付税费_万元": 3862.02,
        "支付其他经营活动现金_万元": 10916.66,
        "经营活动现金流出_万元": 37260.74,
        "经营现金流净额_万元": 2698.26,
        "经营现金流净额同比增长_百分比": -52.67,
        "收回投资现金_万元": 220.48,
        "取得投资收益现金_万元": null,
        "处置资产收回现金_万元": 1.23,
        "收到其他投资活动现金_万元": 25002.73,
        "投资活动现金流入_万元": 25224.44,
        "投资支付现金_万元": null,
        "购建资产支付现金_万元": 12299.57,
        "支付其他投资活动现金_万元": 24158.1,
        "投资活动现金流出_万元": 36457.67,
        "投资现金流净额_万元": -11233.23,
        "吸收投资现金_万元": 300.0,
        "取得借款现金_万元": 34971.89,
        "收到其他筹资活动现金_万元": null,
        "筹资活动现金流入_万元": 35271.89,
        "偿还债务现金_万元": 23000.0,
        "分配股利现金_万元": 402.29,
        "支付其他筹资活动现金_万元": 14.8,
        "筹资活动现金流出_万元": 23417.09,
        "融资现金流净额_万元": 11854.8,
        "汇率变动影响_万元": null,
        "现金及等价物净增加额_万元": 3334.62,
        "净现金流_元": null,
        "净现金流同比增长_百分比": null,
        "期初现金及等价物_万元": 16140.78,
        "期末现金及等价物_万元": 19475.4,
        "经营现金流占比_百分比": null,
        "投资现金流占比_百分比": null,
        "融资现金流占比_百分比": null
    }
}